nzbn/__init__.py
nzbn/abbreviated_entity.py
nzbn/address.py
nzbn/address_type.py
nzbn/classification.py
nzbn/disposition.py
nzbn/entity.py
nzbn/entity_status.py
nzbn/entity_type.py
nzbn/order.py
nzbn/time.py
nzbn/trading_name.py
nzbn/version.py
nzbn/errors/__init__.py
nzbn/errors/api.py
nzbn/errors/error.py
nzbn/errors/type_error.py
nzbn/http/__init__.py
nzbn/http/api_request.py
nzbn/http/method.py
nzbn/http/query_parameter.py
nzbn/http/query_parameters.py
nzbn-1.0.0.dist-info/LICENSE
nzbn-1.0.0.dist-info/METADATA
nzbn-1.0.0.dist-info/WHEEL
nzbn-1.0.0.dist-info/top_level.txt
nzbn-1.0.0.dist-info/RECORD
