Metadata-Version: 2.1
Name: nzbn
Version: 1.0.0
Summary: New Zealand Business Number library
Home-page: https://github.com/procuret/nzbn-python
Author: Procuret
Author-email: hugh@procuret.com
License: UNKNOWN
Project-URL: Github Repository, https://github.com/procuret/nzbn-python
Project-URL: About, https://github.com/procuret/nzbn-python
Keywords: library http api web payments finance nzbn new-zealand nz business business-number
Platform: UNKNOWN
Classifier: Development Status :: 2 - Pre-Alpha
Classifier: Intended Audience :: Developers
Classifier: License :: OSI Approved :: MIT License
Classifier: Natural Language :: English
Classifier: Programming Language :: Python :: 3 :: Only
Classifier: Programming Language :: Python :: 3.7
Classifier: Programming Language :: Python :: 3.8
Classifier: Programming Language :: Python :: 3.9
Classifier: Programming Language :: Python :: 3.10
Classifier: Operating System :: OS Independent
Classifier: Topic :: Software Development :: Libraries
Classifier: Topic :: Office/Business :: Financial
Requires-Python: >=3.6
License-File: LICENSE
